indexurl/__init__.py
indexurl/core.py
indexurl/py.typed
indexurl/tests/__init__.py
indexurl/tests/__main__.py
indexurl/tests/core.py
indexurl-0.9.2.dist-info/LICENSE
indexurl-0.9.2.dist-info/METADATA
indexurl-0.9.2.dist-info/WHEEL
indexurl-0.9.2.dist-info/top_level.txt
indexurl-0.9.2.dist-info/RECORD
