Metadata-Version: 2.1
Name: indexurl
Version: 0.9.2
Summary: Reads index url from pip.conf and infers capabilities
Home-page: https://github.com/python-packaging/indexurl/
Author: Tim Hatch
Author-email: tim@timhatch.com
License: MIT
Requires-Python: >=3.9
License-File: LICENSE
Requires-Dist: appdirs >=1.3.0
Provides-Extra: dev
Requires-Dist: black ==23.12.1 ; extra == 'dev'
Requires-Dist: checkdeps ==0.9.0 ; extra == 'dev'
Requires-Dist: flake8 ==7.0.0 ; extra == 'dev'
Requires-Dist: mypy ==1.8.0 ; extra == 'dev'
Requires-Dist: tox ==4.12.1 ; extra == 'dev'
Requires-Dist: twine ==4.0.2 ; extra == 'dev'
Requires-Dist: ufmt ==2.3.0 ; extra == 'dev'
Requires-Dist: usort ==1.0.7 ; extra == 'dev'
Requires-Dist: wheel ==0.42.0 ; extra == 'dev'
Provides-Extra: test
Requires-Dist: coverage >=6 ; extra == 'test'
